gosdk/__init__.py
gosdk/spec.json
gosdk/testing.py
gosdk-0.11.0.dist-info/METADATA
gosdk-0.11.0.dist-info/WHEEL
gosdk-0.11.0.dist-info/top_level.txt
gosdk-0.11.0.dist-info/RECORD
