Metadata-Version: 2.4
Name: gosdk
Version: 0.11.0
Summary: gosdk
Author-email: Ian Maurer <ian@genomoncology.com>
Classifier: Development Status :: 4 - Beta
Classifier: Intended Audience :: Developers
Classifier: License :: Other/Proprietary License
Classifier: Natural Language :: English
Classifier: Programming Language :: Python
Classifier: Programming Language :: Python :: 3.13
Classifier: Topic :: Scientific/Engineering :: Bio-Informatics
Requires-Python: >=3.13
Requires-Dist: bravado>=12.0.1
Requires-Dist: backoff
Requires-Dist: requests
